arcagent/__init__.py
arcagent/dsl_yusufengintetik.py
arcagent/arc_dsl/00d62c1b.png
arcagent/arc_dsl/5521c0d9.png
arcagent/arc_dsl/LICENSE
arcagent/arc_dsl/README.md
arcagent/arc_dsl/arc_dsl_writeup.pdf
arcagent/arc_dsl/arc_types.py
arcagent/arc_dsl/constants.py
arcagent/arc_dsl/dsl.py
arcagent/arc_dsl/function_length.txt
arcagent/arc_dsl/main.py
arcagent/arc_dsl/result.txt
arcagent/arc_dsl/solver_length.py
arcagent/arc_dsl/solvers.py
arcagent/arc_dsl/solvers_graphs.jsonl
arcagent/arc_dsl/tests.py
arcagent/arc_dsl/translate_solvers.py
arcagent/arc_dsl/vis_solvers.html
arcagent/arc_dsl/arc-vis/.eslintrc.json
arcagent/arc_dsl/arc-vis/.gitignore
arcagent/arc_dsl/arc-vis/README.md
arcagent/arc_dsl/arc-vis/bun.lockb
arcagent/arc_dsl/arc-vis/components.json
arcagent/arc_dsl/arc-vis/next.config.mjs
arcagent/arc_dsl/arc-vis/package.json
arcagent/arc_dsl/arc-vis/postcss.config.mjs
arcagent/arc_dsl/arc-vis/tailwind.config.ts
arcagent/arc_dsl/arc-vis/tsconfig.json
arcagent/arc_dsl/arc-vis/app/Sidebar.tsx
arcagent/arc_dsl/arc-vis/app/favicon.ico
arcagent/arc_dsl/arc-vis/app/globals.css
arcagent/arc_dsl/arc-vis/app/layout.tsx
arcagent/arc_dsl/arc-vis/app/page.tsx
arcagent/arc_dsl/arc-vis/app/solvers_graphs.jsonl
arcagent/arc_dsl/arc-vis/app/[puzzleName]/Notes.tsx
arcagent/arc_dsl/arc-vis/app/[puzzleName]/page.tsx
arcagent/arc_dsl/arc-vis/app/fonts/GeistMonoVF.woff
arcagent/arc_dsl/arc-vis/app/fonts/GeistVF.woff
arcagent/arc_dsl/arc-vis/components/ArcGrid.tsx
arcagent/arc_dsl/arc-vis/components/ArcPuzzle.tsx
arcagent/arc_dsl/arc-vis/components/ArcPuzzleCarousel.tsx
arcagent/arc_dsl/arc-vis/components/Mermaid.tsx
arcagent/arc_dsl/arc-vis/components/NavLink.tsx
arcagent/arc_dsl/arc-vis/components/ui/button.tsx
arcagent/arc_dsl/arc-vis/components/ui/carousel.tsx
arcagent/arc_dsl/arc-vis/components/ui/input.tsx
arcagent/arc_dsl/arc-vis/components/ui/scroll-area.tsx
arcagent/arc_dsl/arc-vis/components/ui/sheet.tsx
arcagent/arc_dsl/arc-vis/data/evaluation/00576224.json
arcagent-0.0.1.dist-info/METADATA
arcagent-0.0.1.dist-info/WHEEL
arcagent-0.0.1.dist-info/entry_points.txt
arcagent-0.0.1.dist-info/RECORD
